context_creator/__init__.py
context_creator/cli.py
context_creator/generator.py
context_creator-1.0.3.dist-info/METADATA
context_creator-1.0.3.dist-info/WHEEL
context_creator-1.0.3.dist-info/entry_points.txt
context_creator-1.0.3.dist-info/top_level.txt
context_creator-1.0.3.dist-info/RECORD
