Metadata-Version: 2.4
Name: context-creator
Version: 1.0.3
Summary: A utility to generate a single context file from a project directory.
Author-email: Ahmed Touhami <mustafachyi272@gmail.com>
License: MIT License
Project-URL: Homepage, https://github.com/mustafachyi/context-creator
Project-URL: Issues, https://github.com/mustafachyi/context-creator/issues
Classifier: Programming Language :: Python :: 3
Classifier: License :: OSI Approved :: MIT License
Classifier: Operating System :: OS Independent
Classifier: Topic :: Utilities
Classifier: Environment :: Console
Requires-Python: >=3.8
Provides-Extra: test
Requires-Dist: pytest; extra == "test"
